MANIFEST.in
setup.py
django_filer_gallery.egg-info/PKG-INFO
django_filer_gallery.egg-info/SOURCES.txt
django_filer_gallery.egg-info/dependency_links.txt
django_filer_gallery.egg-info/not-zip-safe
django_filer_gallery.egg-info/requires.txt
django_filer_gallery.egg-info/top_level.txt
filer_gallery/__init__.py
filer_gallery/admin.py
filer_gallery/models.py
filer_gallery/settings.py
filer_gallery/urls.py
filer_gallery/utils.py
filer_gallery/views.py
filer_gallery/widgets.py
filer_gallery/locale/en/LC_MESSAGES/django.po
filer_gallery/locale/en/LC_MESSAGES/djangojs.po
filer_gallery/static/filer_gallery/fileuploader/fileuploader.css
filer_gallery/static/filer_gallery/fileuploader/fileuploader.js
filer_gallery/static/filer_gallery/fileuploader/loading.gif
filer_gallery/static/filer_gallery/orbit/jquery-1.5.1.min.js
filer_gallery/static/filer_gallery/orbit/jquery.orbit-1.2.3.js
filer_gallery/static/filer_gallery/orbit/jquery.orbit-1.2.3.min.js
filer_gallery/static/filer_gallery/orbit/orbit-1.2.3.css
filer_gallery/static/filer_gallery/orbit/orbit/bullets.jpg
filer_gallery/static/filer_gallery/orbit/orbit/left-arrow.png
filer_gallery/static/filer_gallery/orbit/orbit/loading.gif
filer_gallery/static/filer_gallery/orbit/orbit/mask-black.png
filer_gallery/static/filer_gallery/orbit/orbit/pause-black.png
filer_gallery/static/filer_gallery/orbit/orbit/right-arrow.png
filer_gallery/static/filer_gallery/orbit/orbit/rotator-black.png
filer_gallery/static/filer_gallery/orbit/orbit/timer-black.png
filer_gallery/templates/filer_gallery/filer_gallery_base.html
filer_gallery/templates/filer_gallery/gallery_archive.html
filer_gallery/templates/filer_gallery/gallery_archive_day.html
filer_gallery/templates/filer_gallery/gallery_archive_month.html
filer_gallery/templates/filer_gallery/gallery_archive_year.html
filer_gallery/templates/filer_gallery/gallery_categories_base.html
filer_gallery/templates/filer_gallery/gallery_dates_base.html
filer_gallery/templates/filer_gallery/gallery_list.html
filer_gallery/templates/filer_gallery/gallery_months_links_snippet.html
filer_gallery/templates/filer_gallery/galleryimage_archive.html
filer_gallery/templates/filer_gallery/galleryimage_archive_day.html
