Metadata-Version: 1.0
Name: django-filer-gallery
Version: 1.0.pre-alpha
Summary: A gallery using django-filer
Home-page: http://github.com/fivethreeo/django-filer-gallery.git
Author: Øyvind Saltvik
Author-email: oyvind.saltvik@gmail.com
License: UNKNOWN
Platform: UNKNOWN
Classifier: Development Status :: 4 - Beta
Classifier: Environment :: Web Environment
Classifier: Intended Audience :: Developers
Classifier: License :: OSI Approved :: BSD License
Classifier: Operating System :: OS Independent
Classifier: Programming Language :: Python
Classifier: Framework :: Django
